{
  "2006 1학기 정규": [
    "음영철(컴퓨터학부)",
    "Prof. Williams(컴퓨터학부)",
    "주헌식(컴퓨터학부)",
    "Leander B. Chalice(컴퓨터학부)",
    "Prof. Bissell(컴퓨터학부)",
    "Smith(컴퓨터학부)",
    "허서행(컴퓨터학부)",
    "Prof. Cho(컴퓨터학부)",
    "국중각(컴퓨터학부)",
    "김성완(컴퓨터학부)",
    "미지정(컴퓨터학부)"
  ],
  "2006 2학기 정규": [
    "Prof. Williams(컴퓨터학부)",
    "조양현(컴퓨터학부)",
    "이상엽(컴퓨터학부)",
    "주헌식(컴퓨터학부)",
    "Leander B. Chalice(컴퓨터학부)",
    "Prof. Bissell(컴퓨터학부)",
    "Smith(컴퓨터학부)",
    "신성례(컴퓨터학부)",
    "정수목(컴퓨터학부)",
    "허서행(컴퓨터학부)",
    "Prof. Park(컴퓨터학부)",
    "이정식(컴퓨터학부)",
    "교목처(컴퓨터학부)"
  ],
  "2007 1학기 정규": [
    "Prof. Roberson(컴퓨터학부)",
    "신동근(컴퓨터학부)",
    "Prof. Bacchus(컴퓨터학부)",
    "김희완(컴퓨터학부)",
    "조양현(컴퓨터학부)",
    "김영국(컴퓨터학부)",
    "주헌식(컴퓨터학부)",
    "Baronese Harriet Peters(컴퓨터학부)",
    "이상엽(컴퓨터학부)",
    "Prof. Bissell(컴퓨터학부)",
    "Smith(컴퓨터학부)",
    "김정숙(컴퓨터학부)",
    "정수목(컴퓨터학부)",
    "허서행(컴퓨터학부)",
    "교목처(컴퓨터학부)",
    "국중각(컴퓨터학부)"
  ],
  "2007 2학기 정규": [
    "Pratt(컴퓨터학부)",
    "이상엽(컴퓨터학부)",
    "김정숙(컴퓨터학부)",
    "허서행(컴퓨터학부)",
    "이정식(컴퓨터학부)",
    "Patricia Ann Trude(컴퓨터학부)",
    "조양현(컴퓨터학부)",
    "주헌식(컴퓨터학부)",
    "Koo(컴퓨터학부)",
    "음영철(컴퓨터학부)",
    "신동근(컴퓨터학부)",
    "교목처(컴퓨터학부)",
    "국중각(컴퓨터학부)",
    "김성완(컴퓨터학부)",
    "David O. Heinrich jr(컴퓨터학부)",
    "교류대학(컴퓨터학부)",
    "Jeremiah D. Baptiste(컴퓨터학부)",
    "Baronese Harriet Peters(컴퓨터학부)",
    "이창호(컴퓨터학부)",
    "정수목(컴퓨터학부)"
  ],
  "2008 1학기 정규": [
    "최희식(컴퓨터학부)",
    "박봉곤(컴퓨터학부)",
    "홍경표(컴퓨터학부)",
    "김영국(컴퓨터학부)",
    "이상엽(컴퓨터학부)",
    "김정숙(컴퓨터학부)",
    "허서행(컴퓨터학부)",
    "조양현(컴퓨터학부)",
    "주헌식(컴퓨터학부)",
    "김미연(컴퓨터학부)",
    "신동근(컴퓨터학부)",
    "교목처(컴퓨터학부)",
    "김종경(컴퓨터학부)",
    "국중각(컴퓨터학부)",
    "김성완(컴퓨터학부)",
    "교류대학(컴퓨터학부)",
    "이창호(컴퓨터학부)",
    "이야리(컴퓨터학부)",
    "정수목(컴퓨터학부)"
  ],
  "2008 2학기 정규": [
    "신동근(컴퓨터학부)",
    "교양에서신청(컴퓨터학부)",
    "교류대학(컴퓨터학부)",
    "홍경표(컴퓨터학부)",
    "김희완(컴퓨터학부)",
    "조양현(컴퓨터학부)",
    "국중각(컴퓨터학부)",
    "이상엽(컴퓨터학부)",
    "금연금주클리닉(컴퓨터학부)",
    "주헌식(컴퓨터학부)",
    "정수목(컴퓨터학부)",
    "김정숙(컴퓨터학부)",
    "허서행(컴퓨터학부)",
    "교목처(컴퓨터학부)",
    "이정식(컴퓨터학부)",
    "김성완(컴퓨터학부)"
  ],
  "2009 1학기 정규": [
    "김종완(컴퓨터학부)",
    "신동근(컴퓨터학부)",
    "홍경표(컴퓨터학부)",
    "김희완(컴퓨터학부)",
    "조양현(컴퓨터학부)",
    "김영국(컴퓨터학부)",
    "주헌식(컴퓨터학부)",
    "안인식(컴퓨터학부)",
    "이상엽(컴퓨터학부)",
    "김대영(컴퓨터학부)",
    "정수목(컴퓨터학부)",
    "광운대학교(컴퓨터학부)",
    "김정숙(컴퓨터학부)",
    "한인성(컴퓨터학부)",
    "교목처(컴퓨터학부)",
    "국중각(컴퓨터학부)",
    "김성완(컴퓨터학부)"
  ],
  "2009 2학기 정규": [
    "김영국(컴퓨터학부)",
    "이상엽(컴퓨터학부)",
    "금연금주클리닉(컴퓨터학부)",
    "김대영(컴퓨터학부)",
    "김정숙(컴퓨터학부)",
    "이상홍(컴퓨터학부)",
    "조양현(컴퓨터학부)",
    "엄영현(컴퓨터학부)",
    "주헌식(컴퓨터학부)",
    "안인식(컴퓨터학부)",
    "한인성(컴퓨터학부)",
    "김종완(컴퓨터학부)",
    "신동근(컴퓨터학부)",
    "김희완(컴퓨터학부)",
    "교목처(컴퓨터학부)",
    "국중각(컴퓨터학부)",
    "김성완(컴퓨터학부)",
    "정재화(컴퓨터학부)",
    "박용민(컴퓨터학부)",
    "정수목(컴퓨터학부)"
  ],
  "2010 1학기 정규": [
    "최민석(컴퓨터학부)",
    "신동근(컴퓨터학부)",
    "김희완(컴퓨터학부)",
    "김영국(컴퓨터학부)",
    "조양현(컴퓨터학부)",
    "주헌식(컴퓨터학부)",
    "안인식(컴퓨터학부)",
    "김대영(컴퓨터학부)",
    "이야리(컴퓨터학부)",
    "정수목(컴퓨터학부)",
    "김정숙(컴퓨터학부)",
    "교목처(컴퓨터학부)",
    "이상홍(컴퓨터학부)",
    "이정식(컴퓨터학부)",
    "김성완(컴퓨터학부)",
    "김미수(컴퓨터학부)",
    "이창섭(컴퓨터학부)"
  ],
  "2010 2학기 정규": [
    "김영국(컴퓨터학부)",
    "금연금주클리닉(컴퓨터학부)",
    "김대영(컴퓨터학부)",
    "김정숙(컴퓨터학부)",
    "이상홍(컴퓨터학부)",
    "이정식(컴퓨터학부)",
    "권연진(컴퓨터학부)",
    "정해섭(컴퓨터학부)",
    "조양현(컴퓨터학부)",
    "주헌식(컴퓨터학부)",
    "안인식(컴퓨터학부)",
    "김미수(컴퓨터학부)",
    "신동근(컴퓨터학부)",
    "김희완(컴퓨터학부)",
    "임정준(컴퓨터학부)",
    "교목처(컴퓨터학부)",
    "김성완(컴퓨터학부)",
    "미지정(컴퓨터학부)",
    "이야리(컴퓨터학부)",
    "정수목(컴퓨터학부)",
    "이창섭(컴퓨터학부)"
  ],
  "2011 1학기 정규": [
    "박희만(컴퓨터학부)",
    "신동근(컴퓨터학부)",
    "이정식(컴퓨터학부)",
    "홍순명(컴퓨터학부)",
    "김희완(컴퓨터학부)",
    "김영국(컴퓨터학부)",
    "조양현(컴퓨터학부)",
    "주헌식(컴퓨터학부)",
    "임정준(컴퓨터학부)",
    "김대영(컴퓨터학부)",
    "정수목(컴퓨터학부)",
    "이야리(컴퓨터학부)",
    "김정숙(컴퓨터학부)",
    "교목처(컴퓨터학부)",
    "이상홍(컴퓨터학부)",
    "국중각(컴퓨터학부)",
    "김성완(컴퓨터학부)"
  ],
  "2011 2학기 정규": [
    "김성완(컴퓨터학부)",
    "박희만(컴퓨터학부)",
    "신동근(컴퓨터학부)",
    "비젼드림센터3399-3076(컴퓨터학부)",
    "김희완(컴퓨터학부)",
    "조양현(컴퓨터학부)",
    "김영국(컴퓨터학부)",
    "주헌식(컴퓨터학부)",
    "금연금주클리닉(컴퓨터학부)",
    "정수목(컴퓨터학부)",
    "이야리(컴퓨터학부)",
    "김정숙(컴퓨터학부)",
    "교목처(컴퓨터학부)",
    "국중각(컴퓨터학부)",
    "박병호(컴퓨터학부)"
  ],
  "2012 1학기 정규": [
    "김성완(컴퓨터학부)",
    "최희식(컴퓨터학부)",
    "신동근(컴퓨터학부)",
    "박희만(컴퓨터학부)",
    "비젼드림센터3399-3076(컴퓨터학부)",
    "정현준(컴퓨터학부)",
    "김희완(컴퓨터학부)",
    "조양현(컴퓨터학부)",
    "김영국(컴퓨터학부)",
    "주헌식(컴퓨터학부)",
    "김미연(컴퓨터학부)",
    "정수목(컴퓨터학부)",
    "이야리(컴퓨터학부)",
    "김정숙(컴퓨터학부)",
    "교목처(컴퓨터학부)",
    "국중각(컴퓨터학부)",
    "박병호(컴퓨터학부)",
    "박지연(컴퓨터학부)"
  ],
  "2012 2학기 정규": [
    "최희식(컴퓨터학부)",
    "신동근(컴퓨터학부)",
    "박희만(컴퓨터학부)",
    "봉원영(컴퓨터학부)",
    "정현준(컴퓨터학부)",
    "김희완(컴퓨터학부)",
    "조양현(컴퓨터학부)",
    "김영국(컴퓨터학부)",
    "김미연(컴퓨터학부)",
    "금연금주클리닉(컴퓨터학부)",
    "주헌식(컴퓨터학부)",
    "정수목(컴퓨터학부)",
    "김정숙(컴퓨터학부)",
    "교목처(컴퓨터학부)",
    "김현규(컴퓨터학부)",
    "국중각(컴퓨터학부)",
    "김성완(컴퓨터학부)",
    "미지정(컴퓨터학부)"
  ],
  "2013 1학기 정규": [
    "최희식(컴퓨터학부)",
    "김영국(컴퓨터학부)",
    "cory Allan Wells(컴퓨터학부)",
    "김정숙(컴퓨터학부)",
    "정현준(컴퓨터학부)",
    "조상욱(컴퓨터학부)",
    "조양현(컴퓨터학부)",
    "주헌식(컴퓨터학부)",
    "John Thomas Peters(컴퓨터학부)",
    "박희만(컴퓨터학부)",
    "Hanah Martina Spence(컴퓨터학부)",
    "신동근(컴퓨터학부)",
    "김희완(컴퓨터학부)",
    "국중각(컴퓨터학부)",
    "김성완(컴퓨터학부)",
    "Karen Elizabeth Maberly(컴퓨터학부)",
    "미지정(컴퓨터학부)",
    "정수목(컴퓨터학부)",
    "(컴퓨터학부)",
    "Joan Fay Ballenger(컴퓨터학부)",
    "김현규(컴퓨터학부)"
  ],
  "2013 2학기 정규": [
    "제해종(컴퓨터학부)",
    "최희식(컴퓨터학부)",
    "김영국(컴퓨터학부)",
    "금연금주클리닉(컴퓨터학부)",
    "김정숙(컴퓨터학부)",
    "Sunghee Kim(컴퓨터학부)",
    "Ramez Francis El-Haj(컴퓨터학부)",
    "Valerie Janine S Pratt(컴퓨터학부)",
    "조양현(컴퓨터학부)",
    "주헌식(컴퓨터학부)",
    "박희만(컴퓨터학부)",
    "신동근(컴퓨터학부)",
    "비젼드림센터3399-3076(컴퓨터학부)",
    "김희완(컴퓨터학부)",
    "Andrew Boyne Lee(컴퓨터학부)",
    "교목처(컴퓨터학부)",
    "국중각(컴퓨터학부)",
    "김성완(컴퓨터학부)",
    "정수목(컴퓨터학부)",
    "Moses Donovan Haynes(컴퓨터학부)",
    "(컴퓨터학부)",
    "김현규(컴퓨터학부)"
  ],
  "2014 1학기 정규": [
    "최희식(컴퓨터학부)",
    "김영식(컴퓨터학부)",
    "cory Allan Wells(컴퓨터학부)",
    "김정숙(컴퓨터학부)",
    "정필성(컴퓨터학부)",
    "안병구(컴퓨터학부)",
    "조양현(컴퓨터학부)",
    "주헌식(컴퓨터학부)",
    "John Thomas Peters(컴퓨터학부)",
    "Hanah Martina Spence(컴퓨터학부)",
    "비젼드림센터3399-3076(컴퓨터학부)",
    "김희완(컴퓨터학부)",
    "교목처(컴퓨터학부)",
    "국중각(컴퓨터학부)",
    "김성완(컴퓨터학부)",
    "이희영(컴퓨터학부)",
    "Karen Elizabeth Maberly(컴퓨터학부)",
    "Evan Jurell Hendrix(컴퓨터학부)",
    "부창희(컴퓨터학부)",
    "정수목(컴퓨터학부)",
    "(컴퓨터학부)",
    "Joan Fay Ballenger(컴퓨터학부)",
    "김현규(컴퓨터학부)"
  ],
  "2014 2학기 정규": [
    "최희식(컴퓨터학부)",
    "김영식(컴퓨터학부)",
    "금연금주클리닉(컴퓨터학부)",
    "김정숙(컴퓨터학부)",
    "정필성(컴퓨터학부)",
    "Laetitia Rene Laan(컴퓨터학부)",
    "조양현(컴퓨터학부)",
    "주헌식(컴퓨터학부)",
    "비젼드림센터3399-3076(컴퓨터학부)",
    "김희완(컴퓨터학부)",
    "Paul Laan(컴퓨터학부)",
    "교목처(컴퓨터학부)",
    "국중각(컴퓨터학부)",
    "이희영(컴퓨터학부)",
    "김성완(컴퓨터학부)",
    "Rachel St Justin Magistre(컴퓨터학부)",
    "Shelley Ann October(컴퓨터학부)",
    "Christopher John Wright(컴퓨터학부)",
    "(컴퓨터학부)",
    "정수목(컴퓨터학부)",
    "김현규(컴퓨터학부)"
  ],
  "2015 1학기 정규": [
    "김영식(컴퓨터학부)",
    "금연금주클리닉(컴퓨터학부)",
    "김정숙(컴퓨터학부)",
    "정필성(컴퓨터학부)",
    "SHIN SEUNG WON(컴퓨터학부)",
    "안병구(컴퓨터학부)",
    "조양현(컴퓨터학부)",
    "Kwang Rak Kim(컴퓨터학부)",
    "주헌식(컴퓨터학부)",
    "Kevin Wayne Ellis(컴퓨터학부)",
    "신동근(컴퓨터학부)",
    "Hanah Martina Spence(컴퓨터학부)",
    "김희완(컴퓨터학부)",
    "국중각(컴퓨터학부)",
    "김성완(컴퓨터학부)",
    "이희영(컴퓨터학부)",
    "Evan Jurell Hendrix(컴퓨터학부)",
    "Gillyoung Jung(컴퓨터학부)",
    "정수목(컴퓨터학부)",
    "Moses Donovan Haynes(컴퓨터학부)",
    "(컴퓨터학부)",
    "Joan Fay Ballenger(컴퓨터학부)",
    "김현규(컴퓨터학부)"
  ],
  "2015 2학기 정규": [
    "김영식(컴퓨터학부)",
    "신동근(컴퓨터학부)",
    "국중각(컴퓨터학부)",
    "Valerie Janine S Pratt(컴퓨터학부)",
    "조양현(컴퓨터학부)",
    "Kwang Rak Kim(컴퓨터학부)",
    "김희완(컴퓨터학부)",
    "주헌식(컴퓨터학부)",
    "Gillyoung Jung(컴퓨터학부)",
    "Christopher John Wright(컴퓨터학부)",
    "정수목(컴퓨터학부)",
    "김정숙(컴퓨터학부)",
    "SHIN SEUNG WON(컴퓨터학부)",
    "교목처(컴퓨터학부)",
    "김현규(컴퓨터학부)",
    "William Lagundino(컴퓨터학부)",
    "김성완(컴퓨터학부)",
    "정필성(컴퓨터학부)"
  ],
  "2016 1학기 정규": [
    "최희식(컴퓨터학부)",
    "김영식(컴퓨터학부)",
    "Bernard White(컴퓨터학부)",
    "Gibran M. Hunt(컴퓨터학부)",
    "김정숙(컴퓨터학부)",
    "Clint M. Ratliff(컴퓨터학부)",
    "정필성(컴퓨터학부)",
    "조양현(컴퓨터학부)",
    "Kwang Rak Kim(컴퓨터학부)",
    "주헌식(컴퓨터학부)",
    "Nicole A. Walker(컴퓨터학부)",
    "신동근(컴퓨터학부)",
    "홍성옥(컴퓨터학부)",
    "김희완(컴퓨터학부)",
    "국중각(컴퓨터학부)",
    "William Lagundino(컴퓨터학부)",
    "정원수(컴퓨터학부)",
    "취업정보(컴퓨터학부)",
    "Gillyoung Jung(컴퓨터학부)",
    "정수목(컴퓨터학부)",
    "Ian Robert Jereos Aujero(컴퓨터학부)",
    "(컴퓨터학부)",
    "김현규(컴퓨터학부)"
  ],
  "2016 2학기 정규": [
    "최희식(컴퓨터학부)",
    "김영식(컴퓨터학부)",
    "금연금주클리닉(컴퓨터학부)",
    "김정숙(컴퓨터학부)",
    "정필성(컴퓨터학부)",
    "SHIN SEUNG WON(컴퓨터학부)",
    "Sungoc Evans(컴퓨터학부)",
    "조양현(컴퓨터학부)",
    "Kwang Rak Kim(컴퓨터학부)",
    "주헌식(컴퓨터학부)",
    "Timothy J. Ellis(컴퓨터학부)",
    "신동근(컴퓨터학부)",
    "홍성옥(컴퓨터학부)",
    "인성교육원(컴퓨터학부)",
    "교목처(컴퓨터학부)",
    "국중각(컴퓨터학부)",
    "Rosemarie E. Shin(컴퓨터학부)",
    "Gillyoung Jung(컴퓨터학부)",
    "Christopher John Wright(컴퓨터학부)",
    "정수목(컴퓨터학부)",
    "김현규(컴퓨터학부)"
  ],
  "2017 1학기 정규": [
    "최희식(컴퓨터학부)",
    "김영식(컴퓨터학부)",
    "Ian Robert Jereos Aujero(컴퓨터·메카트로닉스공학부)",
    "국중각(컴퓨터·메카트로닉스공학부)",
    "김정숙(컴퓨터학부)",
    "정필성(컴퓨터학부)",
    "김영식(컴퓨터·메카트로닉스공학부)",
    "김성완(컴퓨터·메카트로닉스공학부)",
    "곽후근(컴퓨터학부)",
    "Andrew Wonho Cho(컴퓨터·메카트로닉스공학부)",
    "신종열(컴퓨터·메카트로닉스공학부)",
    "조양현(컴퓨터학부)",
    "Kwang Rak Kim(컴퓨터학부)",
    "주헌식(컴퓨터학부)",
    "John Thomas Peters(컴퓨터·메카트로닉스공학부)",
    "조양현(컴퓨터·메카트로닉스공학부)",
    "안병구(컴퓨터·메카트로닉스공학부)",
    "김정숙(컴퓨터·메카트로닉스공학부)",
    "교목처(컴퓨터·메카트로닉스공학부)",
    "주헌식(컴퓨터·메카트로닉스공학부)",
    "류한철(컴퓨터·메카트로닉스공학부)",
    "신동근(컴퓨터학부)",
    "홍성옥(컴퓨터학부)",
    "김현규(컴퓨터·메카트로닉스공학부)",
    "교목처(컴퓨터학부)",
    "SHIN SEUNG WON(컴퓨터·메카트로닉스공학부)",
    "국중각(컴퓨터학부)",
    "김성완(컴퓨터학부)",
    "고장혁(컴퓨터·메카트로닉스공학부)",
    "최수경(컴퓨터학부)",
    "계승철(컴퓨터학부)",
    "박정규(컴퓨터학부)",
    "Dillon T. Jones(컴퓨터·메카트로닉스공학부)",
    "Christopher John Wright(컴퓨터·메카트로닉스공학부)",
    "인성교육원(컴퓨터·메카트로닉스공학부)",
    "정수목(컴퓨터·메카트로닉스공학부)",
    "최선순(컴퓨터·메카트로닉스공학부)",
    "정수목(컴퓨터학부)",
    "김현규(컴퓨터학부)",
    "금연금주클리닉(컴퓨터·메카트로닉스공학부)",
    "신동근(컴퓨터·메카트로닉스공학부)",
    "이은영(컴퓨터학부)"
  ],
  "2017 2학기 정규": [
    "김영식(컴퓨터학부)",
    "William Lagundino(컴퓨터·메카트로닉스공학부)",
    "김정숙(컴퓨터학부)",
    "김영식(컴퓨터·메카트로닉스공학부)",
    "김성완(컴퓨터·메카트로닉스공학부)",
    "신종열(컴퓨터·메카트로닉스공학부)",
    "조양현(컴퓨터학부)",
    "Kwang Rak Kim(컴퓨터학부)",
    "주헌식(컴퓨터학부)",
    "김정숙(컴퓨터·메카트로닉스공학부)",
    "교목처(컴퓨터·메카트로닉스공학부)",
    "신동근(컴퓨터학부)",
    "홍성옥(컴퓨터학부)",
    "김현규(컴퓨터·메카트로닉스공학부)",
    "김희완(컴퓨터학부)",
    "Kevin Wayne Ellis(컴퓨터·메카트로닉스공학부)",
    "교목처(컴퓨터학부)",
    "김성완(컴퓨터학부)",
    "Ronda Rose Davids-cromer(컴퓨터·메카트로닉스공학부)",
    "최수경(컴퓨터학부)",
    "계승철(컴퓨터학부)",
    "박정규(컴퓨터학부)",
    "Dillon T. Jones(컴퓨터·메카트로닉스공학부)",
    "정수목(컴퓨터학부)",
    "Joan Fay Ballenger(컴퓨터·메카트로닉스공학부)",
    "김현규(컴퓨터학부)"
  ],
  "2018 1학기 정규": [
    "최희식(컴퓨터학부)",
    "박의진(컴퓨터·메카트로닉스공학부)",
    "김진섭(컴퓨터·메카트로닉스공학부)",
    "김두일(컴퓨터·메카트로닉스공학부)",
    "김정숙(컴퓨터학부)",
    "김성완(컴퓨터·메카트로닉스공학부)",
    "한준탁(컴퓨터학부)",
    "신종열(컴퓨터·메카트로닉스공학부)",
    "조양현(컴퓨터학부)",
    "Kwang Rak Kim(컴퓨터학부)",
    "김승철(컴퓨터·메카트로닉스공학부)",
    "주헌식(컴퓨터학부)",
    "김희완(컴퓨터·메카트로닉스공학부)",
    "조양현(컴퓨터·메카트로닉스공학부)",
    "김정숙(컴퓨터·메카트로닉스공학부)",
    "교목처(컴퓨터·메카트로닉스공학부)",
    "주헌식(컴퓨터·메카트로닉스공학부)",
    "류한철(컴퓨터·메카트로닉스공학부)",
    "홍성옥(컴퓨터학부)",
    "신동근(컴퓨터학부)",
    "김현규(컴퓨터·메카트로닉스공학부)",
    "김희완(컴퓨터학부)",
    "윤병인(컴퓨터·메카트로닉스공학부)",
    "주경진(컴퓨터·메카트로닉스공학부)",
    "교목처(컴퓨터학부)",
    "김두일(컴퓨터학부)",
    "김성완(컴퓨터학부)",
    "(컴퓨터·메카트로닉스공학부)",
    "고장혁(컴퓨터·메카트로닉스공학부)",
    "최수경(컴퓨터학부)",
    "계승철(컴퓨터학부)",
    "정수목(컴퓨터·메카트로닉스공학부)",
    "김현규(컴퓨터학부)",
    "금연금주클리닉(컴퓨터·메카트로닉스공학부)",
    "신동근(컴퓨터·메카트로닉스공학부)"
  ],
  "2018 2학기 정규": [
    "최희식(컴퓨터학부)",
    "박의진(컴퓨터·메카트로닉스공학부)",
    "최수경(컴퓨터·메카트로닉스공학부)",
    "Kwang Rak Kim(컴퓨터·메카트로닉스공학부)",
    "김진섭(컴퓨터·메카트로닉스공학부)",
    "김두일(컴퓨터·메카트로닉스공학부)",
    "김정숙(컴퓨터학부)",
    "김성완(컴퓨터·메카트로닉스공학부)",
    "한준탁(컴퓨터학부)",
    "신종열(컴퓨터·메카트로닉스공학부)",
    "조양현(컴퓨터학부)",
    "Kwang Rak Kim(컴퓨터학부)",
    "주헌식(컴퓨터학부)",
    "김희완(컴퓨터·메카트로닉스공학부)",
    "조양현(컴퓨터·메카트로닉스공학부)",
    "김정숙(컴퓨터·메카트로닉스공학부)",
    "홍성옥(컴퓨터·메카트로닉스공학부)",
    "교목처(컴퓨터·메카트로닉스공학부)",
    "류한철(컴퓨터·메카트로닉스공학부)",
    "신동근(컴퓨터학부)",
    "김희완(컴퓨터학부)",
    "교목처(컴퓨터학부)",
    "김성완(컴퓨터학부)",
    "고장혁(컴퓨터·메카트로닉스공학부)",
    "계승철(컴퓨터학부)",
    "배일진(컴퓨터·메카트로닉스공학부)",
    "정수목(컴퓨터·메카트로닉스공학부)",
    "정수목(컴퓨터학부)"
  ],
  "2019 1학기 정규": [
    "최희식(컴퓨터학부)",
    "오승택(컴퓨터·메카트로닉스공학부)",
    "Kwang Rak Kim(컴퓨터·메카트로닉스공학부)",
    "김두일(컴퓨터·메카트로닉스공학부)",
    "김성완(컴퓨터·메카트로닉스공학부)",
    "김상남(컴퓨터·메카트로닉스공학부)",
    "양민규(컴퓨터·메카트로닉스공학부)",
    "최천수(컴퓨터학부)",
    "계승철(컴퓨터·메카트로닉스공학부)",
    "신종열(컴퓨터·메카트로닉스공학부)",
    "조양현(컴퓨터학부)",
    "Kwang Rak Kim(컴퓨터학부)",
    "김희완(컴퓨터·메카트로닉스공학부)",
    "조양현(컴퓨터·메카트로닉스공학부)",
    "김정숙(컴퓨터·메카트로닉스공학부)",
    "교목처(컴퓨터·메카트로닉스공학부)",
    "주헌식(컴퓨터·메카트로닉스공학부)",
    "류한철(컴퓨터·메카트로닉스공학부)",
    "홍성옥(컴퓨터학부)",
    "신동근(컴퓨터학부)",
    "윤병인(컴퓨터·메카트로닉스공학부)",
    "최희식(컴퓨터·메카트로닉스공학부)",
    "교목처(컴퓨터학부)",
    "고장혁(컴퓨터·메카트로닉스공학부)",
    "최수경(컴퓨터학부)",
    "계승철(컴퓨터학부)",
    "정대성(컴퓨터·메카트로닉스공학부)",
    "정수목(컴퓨터·메카트로닉스공학부)",
    "최선순(컴퓨터·메카트로닉스공학부)",
    "박지훈(컴퓨터·메카트로닉스공학부)",
    "정수목(컴퓨터학부)",
    "곽정무(컴퓨터·메카트로닉스공학부)"
  ],
  "2019 2학기 정규": [
    "오승택(컴퓨터·메카트로닉스공학부)",
    "Kwang Rak Kim(컴퓨터·메카트로닉스공학부)",
    "김정숙(컴퓨터학부)",
    "김성완(컴퓨터·메카트로닉스공학부)",
    "정승권(컴퓨터·메카트로닉스공학부)",
    "신종열(컴퓨터·메카트로닉스공학부)",
    "조양현(컴퓨터학부)",
    "Kwang Rak Kim(컴퓨터학부)",
    "주헌식(컴퓨터학부)",
    "김희완(컴퓨터·메카트로닉스공학부)",
    "조양현(컴퓨터·메카트로닉스공학부)",
    "김정숙(컴퓨터·메카트로닉스공학부)",
    "홍성옥(컴퓨터·메카트로닉스공학부)",
    "교목처(컴퓨터·메카트로닉스공학부)",
    "박춘식(컴퓨터·메카트로닉스공학부)",
    "류한철(컴퓨터·메카트로닉스공학부)",
    "김현규(컴퓨터·메카트로닉스공학부)",
    "최희식(컴퓨터·메카트로닉스공학부)",
    "김성완(컴퓨터학부)",
    "고장혁(컴퓨터·메카트로닉스공학부)",
    "조충희(컴퓨터·메카트로닉스공학부)",
    "정수목(컴퓨터·메카트로닉스공학부)",
    "최선순(컴퓨터·메카트로닉스공학부)",
    "정대성(컴퓨터·메카트로닉스공학부)",
    "이우주(컴퓨터·메카트로닉스공학부)",
    "박지훈(컴퓨터·메카트로닉스공학부)",
    "곽정무(컴퓨터·메카트로닉스공학부)",
    "금연금주클리닉(컴퓨터·메카트로닉스공학부)",
    "신동근(컴퓨터·메카트로닉스공학부)"
  ],
  "2020 1학기 정규": [
    "고기림(컴퓨터공학부)",
    "오승택(컴퓨터·메카트로닉스공학부)",
    "Kwang Rak Kim(컴퓨터·메카트로닉스공학부)",
    "안병구(컴퓨터공학부)",
    "김성완(컴퓨터·메카트로닉스공학부)",
    "김성완(컴퓨터공학부)",
    "정수목(컴퓨터공학부)",
    "양민규(컴퓨터·메카트로닉스공학부)",
    "신동근(컴퓨터공학부)",
    "신종열(컴퓨터·메카트로닉스공학부)",
    "고기림(컴퓨터·메카트로닉스공학부)",
    "김희완(컴퓨터·메카트로닉스공학부)",
    "김정숙(컴퓨터공학부)",
    "조양현(컴퓨터·메카트로닉스공학부)",
    "조양현(컴퓨터공학부)",
    "홍성옥(컴퓨터·메카트로닉스공학부)",
    "윤성림(컴퓨터·메카트로닉스공학부)",
    "안희국(컴퓨터·메카트로닉스공학부)",
    "주헌식(컴퓨터·메카트로닉스공학부)",
    "류한철(컴퓨터·메카트로닉스공학부)",
    "김희완(컴퓨터공학부)",
    "이우주(컴퓨터공학부)",
    "김현규(컴퓨터·메카트로닉스공학부)",
    "최희식(컴퓨터·메카트로닉스공학부)",
    "고청심(컴퓨터·메카트로닉스공학부)",
    "김종국(컴퓨터·메카트로닉스공학부)",
    "고장혁(컴퓨터·메카트로닉스공학부)",
    "김현규(컴퓨터공학부)",
    "조충희(컴퓨터·메카트로닉스공학부)",
    "정수목(컴퓨터·메카트로닉스공학부)",
    "최선순(컴퓨터·메카트로닉스공학부)",
    "Kwang Rak Kim(컴퓨터공학부)",
    "윤형식(컴퓨터·메카트로닉스공학부)"
  ],
  "2020 2학기 정규": [
    "고기림(컴퓨터공학부)",
    "오승택(컴퓨터·메카트로닉스공학부)",
    "Kwang Rak Kim(컴퓨터·메카트로닉스공학부)",
    "김성완(컴퓨터·메카트로닉스공학부)",
    "김성완(컴퓨터공학부)",
    "양민규(컴퓨터·메카트로닉스공학부)",
    "고기림(컴퓨터·메카트로닉스공학부)",
    "김희완(컴퓨터·메카트로닉스공학부)",
    "조양현(컴퓨터·메카트로닉스공학부)",
    "김정숙(컴퓨터·메카트로닉스공학부)",
    "윤성림(컴퓨터·메카트로닉스공학부)",
    "주헌식(컴퓨터·메카트로닉스공학부)",
    "정성은(컴퓨터·메카트로닉스공학부)",
    "류한철(컴퓨터·메카트로닉스공학부)",
    "김현규(컴퓨터·메카트로닉스공학부)",
    "최희식(컴퓨터·메카트로닉스공학부)",
    "고청심(컴퓨터·메카트로닉스공학부)",
    "김종국(컴퓨터·메카트로닉스공학부)",
    "고장혁(컴퓨터·메카트로닉스공학부)",
    "정성은(컴퓨터공학부)",
    "고청심(컴퓨터공학부)",
    "정수목(컴퓨터·메카트로닉스공학부)",
    "최선순(컴퓨터·메카트로닉스공학부)",
    "이우주(컴퓨터·메카트로닉스공학부)",
    "장세환(컴퓨터·메카트로닉스공학부)",
    "윤형식(컴퓨터·메카트로닉스공학부)",
    "조충희(컴퓨터공학부)",
    "신동근(컴퓨터·메카트로닉스공학부)"
  ],
  "2021 1학기 정규": [
    "고기림(컴퓨터공학부)",
    "오승택(컴퓨터·메카트로닉스공학부)",
    "최희식(컴퓨터공학부)",
    "안병구(컴퓨터공학부)",
    "김성완(컴퓨터·메카트로닉스공학부)",
    "김성완(컴퓨터공학부)",
    "정수목(컴퓨터공학부)",
    "고기림(컴퓨터·메카트로닉스공학부)",
    "김희완(컴퓨터·메카트로닉스공학부)",
    "김정숙(컴퓨터공학부)",
    "조양현(컴퓨터·메카트로닉스공학부)",
    "김정숙(컴퓨터·메카트로닉스공학부)",
    "홍성옥(컴퓨터·메카트로닉스공학부)",
    "주헌식(컴퓨터·메카트로닉스공학부)",
    "고성현(컴퓨터·메카트로닉스공학부)",
    "류한철(컴퓨터·메카트로닉스공학부)",
    "김희완(컴퓨터공학부)",
    "이우주(컴퓨터공학부)",
    "김현규(컴퓨터·메카트로닉스공학부)",
    "이주환(컴퓨터공학부)",
    "김종국(컴퓨터·메카트로닉스공학부)",
    "고장혁(컴퓨터·메카트로닉스공학부)",
    "정성은(컴퓨터공학부)",
    "고청심(컴퓨터공학부)",
    "조충희(컴퓨터·메카트로닉스공학부)",
    "정수목(컴퓨터·메카트로닉스공학부)",
    "최선순(컴퓨터·메카트로닉스공학부)",
    "장세환(컴퓨터·메카트로닉스공학부)",
    "김현규(컴퓨터공학부)",
    "신동근(컴퓨터·메카트로닉스공학부)"
  ],
  "2021 2학기 정규": [
    "고기림(컴퓨터공학부)",
    "김성완(컴퓨터·메카트로닉스공학부)",
    "정승권(컴퓨터·메카트로닉스공학부)",
    "강준호(컴퓨터·메카트로닉스공학부)",
    "김성완(컴퓨터공학부)",
    "정수목(컴퓨터공학부)",
    "고기림(컴퓨터·메카트로닉스공학부)",
    "김희완(컴퓨터·메카트로닉스공학부)",
    "김정숙(컴퓨터공학부)",
    "조양현(컴퓨터공학부)",
    "김정숙(컴퓨터·메카트로닉스공학부)",
    "주헌식(컴퓨터·메카트로닉스공학부)",
    "정성은(컴퓨터·메카트로닉스공학부)",
    "류한철(컴퓨터·메카트로닉스공학부)",
    "김희완(컴퓨터공학부)",
    "미지정(컴퓨터공학부)",
    "이우주(컴퓨터공학부)",
    "김현규(컴퓨터·메카트로닉스공학부)",
    "최희식(컴퓨터·메카트로닉스공학부)",
    "손정혜(컴퓨터공학부)",
    "김종국(컴퓨터·메카트로닉스공학부)",
    "고장혁(컴퓨터·메카트로닉스공학부)",
    "정성은(컴퓨터공학부)",
    "손정혜(컴퓨터·메카트로닉스공학부)",
    "홍성옥(컴퓨터공학부)",
    "정수목(컴퓨터·메카트로닉스공학부)",
    "최선순(컴퓨터·메카트로닉스공학부)",
    "김현규(컴퓨터공학부)",
    "신동근(컴퓨터·메카트로닉스공학부)"
  ],
  "2022 1학기 정규": [
    "고기림(컴퓨터공학부)",
    "최희식(컴퓨터공학부)",
    "김성완(컴퓨터·메카트로닉스공학부)",
    "이한청(컴퓨터공학부)",
    "강준호(컴퓨터·메카트로닉스공학부)",
    "박만재(컴퓨터·메카트로닉스공학부)",
    "김성완(컴퓨터공학부)",
    "정수목(컴퓨터공학부)",
    "신동근(컴퓨터공학부)",
    "고기림(컴퓨터·메카트로닉스공학부)",
    "김희완(컴퓨터·메카트로닉스공학부)",
    "김정숙(컴퓨터공학부)",
    "조양현(컴퓨터·메카트로닉스공학부)",
    "윤병인(컴퓨터공학부)",
    "홍성옥(컴퓨터·메카트로닉스공학부)",
    "류한철(컴퓨터·메카트로닉스공학부)",
    "김희완(컴퓨터공학부)",
    "김현규(컴퓨터·메카트로닉스공학부)",
    "최희식(컴퓨터·메카트로닉스공학부)",
    "손정혜(컴퓨터공학부)",
    "김종국(컴퓨터·메카트로닉스공학부)",
    "고장혁(컴퓨터·메카트로닉스공학부)",
    "손정혜(컴퓨터·메카트로닉스공학부)",
    "주헌식(컴퓨터공학부)",
    "최선순(컴퓨터·메카트로닉스공학부)",
    "김현규(컴퓨터공학부)"
  ],
  "2022 2학기 정규": [
    "고기림(컴퓨터공학부)",
    "김성완(컴퓨터공학부)",
    "이한청(컴퓨터공학부)",
    "정수목(컴퓨터공학부)",
    "주헌식(컴퓨터·메카트로닉스공학부)",
    "고장혁(컴퓨터·메카트로닉스공학부)",
    "신동근(컴퓨터공학부)",
    "김희완(컴퓨터공학부)",
    "김현규(컴퓨터·메카트로닉스공학부)",
    "손정혜(컴퓨터·메카트로닉스공학부)",
    "홍성옥(컴퓨터공학부)",
    "최희식(컴퓨터·메카트로닉스공학부)",
    "최희식(컴퓨터공학부)",
    "김정숙(컴퓨터공학부)",
    "김현규(컴퓨터공학부)",
    "조충희(컴퓨터공학부)",
    "신동근(컴퓨터·메카트로닉스공학부)",
    "손정혜(컴퓨터공학부)"
  ],
  "2023 1학기 정규": [
    "고기림(컴퓨터공학부)",
    "김용승(컴퓨터공학부)",
    "이근정(컴퓨터공학부)",
    "최희식(컴퓨터공학부)",
    "최민석(컴퓨터공학부)",
    "이한청(컴퓨터공학부)",
    "김성완(컴퓨터공학부)",
    "정수목(컴퓨터공학부)",
    "신동근(컴퓨터공학부)",
    "오성규(컴퓨터공학부)",
    "김정숙(컴퓨터공학부)",
    "조양현(컴퓨터공학부)",
    "김진호(컴퓨터공학부)",
    "우별림(컴퓨터공학부)",
    "남윤진(컴퓨터공학부)",
    "이선순(컴퓨터공학부)",
    "손정혜(컴퓨터공학부)",
    "주헌식(컴퓨터공학부)",
    "김현규(컴퓨터공학부)",
    "조충희(컴퓨터공학부)"
  ]
}